five_temp/__init__.py
five_temp/cli.py
five_temp/core.py
five_temp/encrypt.py
fivetemp-1.0.9.dist-info/LICENSE
fivetemp-1.0.9.dist-info/METADATA
fivetemp-1.0.9.dist-info/WHEEL
fivetemp-1.0.9.dist-info/entry_points.txt
fivetemp-1.0.9.dist-info/top_level.txt
fivetemp-1.0.9.dist-info/RECORD
